vivintpy/__init__.py
vivintpy/account.py
vivintpy/api.py
vivintpy/const.py
vivintpy/devices/__init__.py
vivintpy/devices/alarm_panel.py
vivintpy/devices/camera.py
vivintpy/devices/door_lock.py
vivintpy/devices/garage_door.py
vivintpy/devices/switch.py
vivintpy/devices/thermostat.py
vivintpy/devices/wireless_sensor.py
vivintpy/entity.py
vivintpy/enums.py
vivintpy/exceptions.py
vivintpy/proto/beam_pb2.py
vivintpy/proto/beam_pb2.pyi
vivintpy/proto/beam_pb2_grpc.py
vivintpy/pubnub.py
vivintpy/py.typed
vivintpy/system.py
vivintpy/user.py
vivintpy/utils.py
vivintpy/zjs_device_config_db.json
vivintpy/zjs_device_config_db.py
vivintpy-2026.0.1.dist-info/METADATA
vivintpy-2026.0.1.dist-info/WHEEL
vivintpy-2026.0.1.dist-info/licenses/LICENSE
vivintpy-2026.0.1.dist-info/RECORD
