Metadata-Version: 2.4
Name: vivintpy
Version: 2026.0.1
Summary: Python library for interacting with a Vivint security and smart home system.
License-Expression: MIT
License-File: LICENSE
Keywords: Vivint,alarm system,security,smart home,home automation,asynchronous
Author: Nathan Spencer
Author-email: natekspencer@gmail.com
Requires-Python: >=3.10
Classifier: Programming Language :: Python :: 3
Classifier: Programming Language :: Python :: 3.10
Classifier: Programming Language :: Python :: 3.11
Classifier: Programming Language :: Python :: 3.12
Classifier: Programming Language :: Python :: 3.13
Classifier: Programming Language :: Python :: 3.14
Requires-Dist: aiohttp (>=3.8.5)
Requires-Dist: certifi (>=2022.9.24)
Requires-Dist: grpcio (>=1.51.1)
Requires-Dist: protobuf (>=4.23.1)
Requires-Dist: pubnub (>=7)
Requires-Dist: pyjwt (>=2.9.0)
Project-URL: Homepage, https://github.com/natekspencer/vivintpy
Project-URL: Repository, https://github.com/natekspencer/vivintpy
